library.core-2.1.6-py3.12-nspkg.pth
library/core/__init__.py
library/core/commentextender.py
library/core/configure.zcml
library/core/indexers.py
library/core/indexers.zcml
library/core/interfaces.py
library/core/permissions.zcml
library/core/setuphandlers.py
library/core/subscribers.py
library/core/subscribers.zcml
library/core/testing.py
library/core/testing.zcml
library/core/utils.py
library/core/vocabularies.py
library/core/browser/__init__.py
library/core/browser/configure.zcml
library/core/browser/faceted/__init__.py
library/core/browser/faceted/configure.zcml
library/core/browser/faceted/map.pt
library/core/browser/faceted/map.py
library/core/browser/overrides/.gitkeep
library/core/browser/static/.gitkeep
library/core/content/__init__.py
library/core/content/configure.zcml
library/core/content/patrimoine.py
library/core/content/patrimoine.xml
library/core/content/templates/contenus_lies.pt
library/core/content/templates/patrimoine.pt
library/core/locales/README.rst
library/core/locales/__init__.py
library/core/locales/library.core.pot
library/core/locales/update.py
library/core/locales/update.sh
library/core/locales/en/LC_MESSAGES/library.core.po
library/core/locales/fr/LC_MESSAGES/library.core.po
library/core/profiles/default/browserlayer.xml
library/core/profiles/default/catalog.xml
library/core/profiles/default/metadata.xml
library/core/profiles/default/registry.xml
library/core/profiles/default/rolemap.xml
library/core/profiles/default/types.xml
library/core/profiles/default/types/patrimoine.xml
library/core/profiles/uninstall/browserlayer.xml
library/core/tests/__init__.py
library/core/tests/test_geolocation.py
library/core/tests/test_patrimoine.py
library/core/tests/test_setup.py
library/core/tiles/configure.zcml
library/core/tiles/existingcontent.py
library/core/upgrades/__init__.py
library/core/upgrades/configure.zcml
library/core/upgrades/upgrades.py
library/core/upgrades/profiles/1003_to_1004/types/patrimoine.xml
library/core/viewlets/comments.pt
library_core-2.1.6.dist-info/licenses/LICENSE.GPL
library_core-2.1.6.dist-info/licenses/LICENSE.rst
library_core-2.1.6.dist-info/METADATA
library_core-2.1.6.dist-info/WHEEL
library_core-2.1.6.dist-info/entry_points.txt
library_core-2.1.6.dist-info/namespace_packages.txt
library_core-2.1.6.dist-info/top_level.txt
library_core-2.1.6.dist-info/RECORD
