Metadata-Version: 2.4
Name: library.core
Version: 2.1.6
Summary: Core package for Bibliotheca
Home-page: https://pypi.python.org/pypi/library.core
Author: Nicolas Demonte
Author-email: support@imio.be
License: GPL version 2
Keywords: Python Plone
Classifier: Environment :: Web Environment
Classifier: Framework :: Plone
Classifier: Framework :: Plone :: 6.0
Classifier: Framework :: Plone :: Addon
Classifier: Programming Language :: Python
Classifier: Programming Language :: Python :: 3.8
Classifier: Programming Language :: Python :: 3.9
Classifier: Programming Language :: Python :: 3.10
Classifier: Operating System :: OS Independent
Classifier: License :: OSI Approved :: GNU General Public License v2 (GPLv2)
License-File: LICENSE.GPL
License-File: LICENSE.rst
Requires-Dist: plone.api>=1.8.4
Requires-Dist: plone.restapi
Requires-Dist: Products.GenericSetup>=1.8.2
Requires-Dist: setuptools
Requires-Dist: z3c.jbot
Requires-Dist: z3c.unconfigure
Requires-Dist: plone.app.discussion
Requires-Dist: collective.behavior.gallery
Requires-Dist: collective.geolocationbehavior
Requires-Dist: collective.taxonomy
Requires-Dist: collective.z3cform.select2>=3.0.0b6
Requires-Dist: collective.faceted.map
Requires-Dist: iaweb.mosaic
Provides-Extra: test
Requires-Dist: plone.app.testing; extra == "test"
Requires-Dist: plone.restapi; extra == "test"
Requires-Dist: plone.testing>=5.0.0; extra == "test"
Requires-Dist: plone.app.contenttypes; extra == "test"
Requires-Dist: plone.app.robotframework[debug]; extra == "test"
Dynamic: author
Dynamic: author-email
Dynamic: classifier
Dynamic: description
Dynamic: home-page
Dynamic: keywords
Dynamic: license
Dynamic: license-file
Dynamic: provides-extra
Dynamic: requires-dist
Dynamic: summary
